README.md
setup.cfg
setup.py
pip_additions/__init__.py
pip_additions/installs.py
pip_additions/parsing.py
pip_additions.egg-info/PKG-INFO
pip_additions.egg-info/SOURCES.txt
pip_additions.egg-info/dependency_links.txt
pip_additions.egg-info/requires.txt
pip_additions.egg-info/top_level.txt