Metadata-Version: 1.1
Name: pip-additions
Version: 0.2
Summary: Additional Pip Utilities
Home-page: https://github.com/michaeldistler/pip-additions
Author: Michael Distler
Author-email: michael.distler@gmail.com
License: UNKNOWN
Download-URL: https://github.com/michaeldistler/pip-additions/archive/0.1.tar.gz
Platform: UNKNOWN
